aidev_bkplugin-1.0.13.dist-info/METADATA
aidev_bkplugin-1.0.13.dist-info/WHEEL
aidev_bkplugin-1.0.13.dist-info/entry_points.txt
aidev_bkplugin/__init__.py
aidev_bkplugin/apps.py
aidev_bkplugin/migrations/__init__.py
aidev_bkplugin/openapi/__init__.py
aidev_bkplugin/openapi/urls.py
aidev_bkplugin/openapi/views.py
aidev_bkplugin/packages/__init__.py
aidev_bkplugin/packages/apigw/__init__.py
aidev_bkplugin/packages/apigw/permissions.py
aidev_bkplugin/packages/drf/__init__.py
aidev_bkplugin/packages/drf/exception.py
aidev_bkplugin/packages/opentelemetry/__init__.py
aidev_bkplugin/packages/opentelemetry/callback_handler.py
aidev_bkplugin/packages/opentelemetry/config.py
aidev_bkplugin/packages/opentelemetry/instrumentor.py
aidev_bkplugin/packages/opentelemetry/otel_service.py
aidev_bkplugin/packages/opentelemetry/span_utils.py
aidev_bkplugin/packages/opentelemetry/utils.py
aidev_bkplugin/permissions.py
aidev_bkplugin/services/__init__.py
aidev_bkplugin/services/agent.py
aidev_bkplugin/services/factory.py
aidev_bkplugin/settings.py
aidev_bkplugin/urls.py
aidev_bkplugin/utils.py
aidev_bkplugin/views/__init__.py
aidev_bkplugin/views/builtin.py
aidev_bkplugin-1.0.13.dist-info/RECORD
