Metadata-Version: 2.1
Name: aidev-bkplugin
Version: 1.0.13
Summary: AiDev Agent Bkplugin builtin functions
Requires-Python: <4,>=3.11.9
Requires-Dist: aidev-agent<1.1,>=1.0.6
Requires-Dist: blueapps<5.0,>=4.15.1
